synthlang/__init__.py
synthlang/cli.py
synthlang/core.py
synthlang/evaluator.py
synthlang/executor.py
synthlang/monitor.py
synthlang/optimization.py
synthlang/parser.py
synthlang_mbc-1.0.0.dist-info/licenses/LICENSE
synthlang_mbc-1.0.0.dist-info/METADATA
synthlang_mbc-1.0.0.dist-info/WHEEL
synthlang_mbc-1.0.0.dist-info/entry_points.txt
synthlang_mbc-1.0.0.dist-info/top_level.txt
synthlang_mbc-1.0.0.dist-info/RECORD
